porndetective/LICENSE
porndetective/LoadWay.py
porndetective/PornError.py
porndetective/TestCase.py
porndetective/__init__.py
porndetective/porn_detective.log
porndetective/scan_result.txt
porndetective/test.jpg
porndetective/test_Normal.jpg
porndetective-1.0.5.dist-info/DESCRIPTION.rst
porndetective-1.0.5.dist-info/METADATA
porndetective-1.0.5.dist-info/RECORD
porndetective-1.0.5.dist-info/WHEEL
porndetective-1.0.5.dist-info/metadata.json
porndetective-1.0.5.dist-info/top_level.txt
