Metadata-Version: 2.0
Name: porndetective
Version: 1.0.5
Summary: provide service for detecting porn picture
Home-page: UNKNOWN
Author: LouisSong
Author-email: slysly759@gmail.com
License: Apache License
Keywords: detect porn,Pattern recognition
Platform: Python3.x
Requires-Dist: requests
